irl.py
irl-0.2.dist-info/LICENSE
irl-0.2.dist-info/METADATA
irl-0.2.dist-info/WHEEL
irl-0.2.dist-info/top_level.txt
irl-0.2.dist-info/RECORD
