Metadata-Version: 2.1
Name: irl
Version: 0.2
Summary: UNKNOWN
Home-page: UNKNOWN
Author: Seth Michael Larson
Author-email: sethmichaellarson@gmail.com
License: MIT
Platform: UNKNOWN
Requires-Python: >=3.6
